pyhud/__init__.py
hud_python_sdk-0.0.0a0.dist-info/METADATA
hud_python_sdk-0.0.0a0.dist-info/WHEEL
hud_python_sdk-0.0.0a0.dist-info/top_level.txt
hud_python_sdk-0.0.0a0.dist-info/RECORD
